expiry_addon/__init__.py
expiry_addon/admin.py
expiry_addon/apps.py
expiry_addon/constants.py
expiry_addon/models.py
expiry_addon/run_startup.py
expiry_addon/serializers.py
expiry_addon/signals.py
expiry_addon/tests.py
expiry_addon/urls.py
expiry_addon/views.py
expiry_addon/migrations/0001_initial.py
expiry_addon/migrations/0002_auto_20220711_1038.py
expiry_addon/migrations/0003_resourceexpirypolicy_current_expiry_date.py
expiry_addon/migrations/__init__.py
expiry_addon/startup/__init__.py
expiry_addon/startup/lr_action_utils.py
expiry_addon/templates/expiry_addon/dropdown.html
expiry_addon/templates/expiry_addon/info.html
expiry_addon/templates/expiry_addon/modal.html
rlocker_expiryaddon-0.1.2.dist-info/METADATA
rlocker_expiryaddon-0.1.2.dist-info/WHEEL
rlocker_expiryaddon-0.1.2.dist-info/top_level.txt
rlocker_expiryaddon-0.1.2.dist-info/RECORD
