Metadata-Version: 2.1
Name: rlocker-expiryaddon
Version: 0.1.2
Summary: A Plugin for Resource Locker Project to implement expiry logic
Home-page: https://github.com/jimdevops19/rlocker_expiry_addon.git
Download-URL: https://pypi.org/project/rlocker_expiry_addon/
Author: Jim Erginbash
Author-email: jimshapedcoding@gmail.com
License: MIT
Keywords: Rlocker,rlocker,ResourceLocker,Python 3,Resource Locker
